fed_net_liquidity/__init__.py
fed_net_liquidity/fed_net_liquidity.py
fed_net_liquidity/update.py
fed_net_liquidity-0.0.3.dist-info/METADATA
fed_net_liquidity-0.0.3.dist-info/WHEEL
fed_net_liquidity-0.0.3.dist-info/licenses/LICENSE
fed_net_liquidity-0.0.3.dist-info/RECORD
