Metadata-Version: 2.3
Name: fed_net_liquidity
Version: 0.0.3
Summary: Library for calculating Fed Net Liquidity
Project-URL: Homepage, https://github.com/dharmatech/fed_net_liquidity.py
Project-URL: Issues, https://github.com/dharmatech/fed_net_liquidity.py/issues
Author-email: Eduardo Cavazos <wayo.cavazos@gmail.com>
License-File: LICENSE
Classifier: License :: OSI Approved :: MIT License
Classifier: Operating System :: OS Independent
Classifier: Programming Language :: Python :: 3
Requires-Python: >=3.8
Requires-Dist: fred-pandas
Requires-Dist: newyorkfed-pandas
Requires-Dist: pandas
Requires-Dist: requests
Requires-Dist: treasury-gov-pandas
